gsheetstables/__init__.py
gsheetstables/__main__.py
gsheetstables-2.3.dist-info/licenses/LICENSE
gsheetstables-2.3.dist-info/METADATA
gsheetstables-2.3.dist-info/WHEEL
gsheetstables-2.3.dist-info/entry_points.txt
gsheetstables-2.3.dist-info/top_level.txt
gsheetstables-2.3.dist-info/RECORD
