Metadata-Version: 2.4
Name: gsheetstables
Version: 2.3
Summary: Access the Tables of your Google Sheets as Pandas Dataframes and write them to a database
Author-email: Avi Alkalay <avi@unix.sh>
Project-URL: Homepage, https://github.com/avibrazil/autorsync
Project-URL: Source, https://github.com/avibrazil/autorsync
Project-URL: Issues, https://github.com/avibrazil/autorsync/issues/new/choose
Project-URL: Pypi, https://pypi.org/project/auto-remote-sync
Classifier: Programming Language :: Python :: 3
Classifier: Operating System :: OS Independent
Classifier: Development Status :: 5 - Production/Stable
Classifier: Environment :: MacOS X
Classifier: Environment :: Win32 (MS Windows)
Classifier: Environment :: Console
Classifier: Intended Audience :: System Administrators
Classifier: Intended Audience :: End Users/Desktop
Classifier: License :: OSI Approved :: GNU Library or Lesser General Public License (LGPL)
Classifier: Operating System :: MacOS
Classifier: Operating System :: Microsoft :: Windows
Classifier: Operating System :: POSIX
Classifier: Operating System :: Unix
Classifier: Topic :: System :: Archiving :: Backup
Classifier: Topic :: System :: Recovery Tools
Requires-Python: >=3.7
License-File: LICENSE
Requires-Dist: Unidecode
Requires-Dist: dotmap
Requires-Dist: pandas
Requires-Dist: google-auth-oauthlib
Requires-Dist: google-api-python-client
Requires-Dist: Jinja2
Requires-Dist: SQLAlchemy
Dynamic: license-file
